README.md
setup.py
django_migration_testcase/__init__.py
django_migration_testcase/base.py
django_migration_testcase/django_migrations.py
django_migration_testcase/south_migrations.py
django_migration_testcase.egg-info/PKG-INFO
django_migration_testcase.egg-info/SOURCES.txt
django_migration_testcase.egg-info/dependency_links.txt
django_migration_testcase.egg-info/requires.txt
django_migration_testcase.egg-info/top_level.txt