Metadata-Version: 1.1
Name: django-migration-testcase
Version: 0.0.15
Summary: For testing migrations in Django
Home-page: https://github.com/plumdog/django_migration_testcase
Author: Andrew Plummer
Author-email: plummer574@gmail.com
License: UNKNOWN
Platform: UNKNOWN
Classifier: Programming Language :: Python
Classifier: Programming Language :: Python :: 2.7
Classifier: Programming Language :: Python :: 3
Classifier: Programming Language :: Python :: 3.4
Classifier: Programming Language :: Python :: 3.5
Classifier: Programming Language :: Python :: 3.6
Classifier: Programming Language :: Python :: 3.7
